setup.cfg
setup.py
sqlalchemy_validation/__init__.py
sqlalchemy_validation/attribute.py
sqlalchemy_validation/column.py
sqlalchemy_validation/error.py
sqlalchemy_validation/model.py
sqlalchemy_validation/util.py
sqlalchemy_validation/validate_column.py
sqlalchemy_validation.egg-info/PKG-INFO
sqlalchemy_validation.egg-info/SOURCES.txt
sqlalchemy_validation.egg-info/dependency_links.txt
sqlalchemy_validation.egg-info/requires.txt
sqlalchemy_validation.egg-info/top_level.txt
sqlalchemy_validation.egg-info/zip-safe