Metadata-Version: 1.0
Name: sqlalchemy-validation
Version: 0.4.0a0
Summary: This library supports validations based on the model class's definition.
Home-page: https://github.com/minimum-core/sqlalchemy-validation
Author: Suzuki Shunsuke
Author-email: suzuki.shunsuke.1989@gmail.com
License: MIT
Keywords: validation sqlalchemy
Platform: UNKNOWN
